{
  "global": [
    {
      "timestamp": 1736281835992,
      "score": 4
    },
    {
      "timestamp": 1736282075591,
      "score": 0
    },
    {
      "timestamp": 1736356040839,
      "score": 5
    },
    {
      "timestamp": 1737973163800,
      "score": 0
    },
    {
      "timestamp": 1745592235312,
      "score": 1
    },
    {
      "timestamp": 1746311246263,
      "score": 0
    },
    {
      "timestamp": 1746311361739,
      "score": 0
    },
    {
      "timestamp": 1747673488084,
      "score": 1
    },
    {
      "timestamp": 1747673912661,
      "score": 3
    }
  ],
  "users": {}
}